<?xml version="1.0" encoding="utf-8"?>
<LanguageData>
  <HC_WonSlotMachineGame.stages.won_a_game_of_slots.label>gane un juegos tragamonedas</HC_WonSlotMachineGame.stages.won_a_game_of_slots.label>
  <HC_WonSlotMachineGame.stages.won_a_game_of_slots.description>He tenido algo de suerte en las máquinas tragamonedas!</HC_WonSlotMachineGame.stages.won_a_game_of_slots.description>
  <RiggedSlotmachine.stages.rigged_slotmachine.label>máquinas tragamonedas amañadas</RiggedSlotmachine.stages.rigged_slotmachine.label>
  <RiggedSlotmachine.stages.rigged_slotmachine.description>Empiezo a creer que las máquinas tragamonedas están amañadas.</RiggedSlotmachine.stages.rigged_slotmachine.description>
  <GenerousSlotmachine.stages.generous_slotmachine.label>máquinas tragamonedas generosas</GenerousSlotmachine.stages.generous_slotmachine.label>
  <GenerousSlotmachine.stages.generous_slotmachine.description>Siento que las maquinas tragamonedas han estado muy generosas hoy.</GenerousSlotmachine.stages.generous_slotmachine.description>
</LanguageData>